{"2023-12-06-2023-12-06": {"VEN - Nicolás Maduro - TW": [{"valor": 84, "palabra": "presidente-nicolás-maduro"}, {"valor": 58, "palabra": "república-bolivariana-venezuela"}, {"valor": 44, "palabra": "presidente-guyana-irfaan"}, {"valor": 38, "palabra": "venezuela-nicolás-maduro"}, {"valor": 36, "palabra": "consejo-federal-gobierno"}, {"valor": 30, "palabra": "elegido-presidente-venezuela"}, {"valor": 29, "palabra": "estado-guayana-esequiba"}, {"valor": 28, "palabra": "defensa-guayana-esequiba"}, {"valor": 28, "palabra": "asamblea-general-consejo"}, {"valor": 28, "palabra": "general-consejo-federal"}, {"valor": 26, "palabra": "venezuela-esequibo-nuestro"}, {"valor": 25, "palabra": "nuestra-guayana-esequiba"}, {"valor": 25, "palabra": "territorio-guayana-esequiba"}, {"valor": 23, "palabra": "presidente-venezuela-nicolás"}, {"valor": 21, "palabra": "declaraciones-presidente-irfaan"}, {"valor": 20, "palabra": "esequibo-nuestro-venezuela"}, {"valor": 20, "palabra": "comando-estados-unidos"}, {"valor": 20, "palabra": "nicolás-maduro-lideró"}, {"valor": 20, "palabra": "maduro-lideró-asamblea"}, {"valor": 20, "palabra": "lideró-asamblea-general"}, {"valor": 18, "palabra": "nicolás-maduro-ordenó"}, {"valor": 18, "palabra": "recientes-declaraciones-presidente"}, {"valor": 17, "palabra": "defensa-nuestro-territorio"}, {"valor": 17, "palabra": "defensa-integral-guayana"}, {"valor": 17, "palabra": "venezuela-condena-recientes"}, {"valor": 17, "palabra": "condena-recientes-declaraciones"}, {"valor": 17, "palabra": "manera-irresponsable-presencia"}, {"valor": 17, "palabra": "irresponsable-presencia-comando"}, {"valor": 17, "palabra": "presencia-comando-estados"}, {"valor": 16, "palabra": "oficial-república-bolivariana"}], "VEN - Referendo Guyana - TW": [{"valor": 138, "palabra": "república-bolivariana-venezuela"}, {"valor": 78, "palabra": "venezuela-esequibo-nuestro"}, {"valor": 64, "palabra": "esequibo-nuestro-venezuela"}, {"valor": 60, "palabra": "venezuela-esequibo-venezuela"}, {"valor": 45, "palabra": "bolivariana-venezuela-resultado"}, {"valor": 37, "palabra": "esequibo-venezuela-esequibo"}, {"valor": 35, "palabra": "oficial-república-bolivariana"}, {"valor": 35, "palabra": "esequibo-venezuela-venezuela"}, {"valor": 34, "palabra": "venezuela-venezuela-esequibo"}, {"valor": 34, "palabra": "resultado-referendo-consultivo"}, {"valor": 33, "palabra": "tensión-venezuela-guyana"}, {"valor": 32, "palabra": "venezuela-guyana-maduro"}, {"valor": 31, "palabra": "esequibo-siempre-venezuela"}, {"valor": 31, "palabra": "venezuela-resultado-referendo"}, {"valor": 30, "palabra": "conoce-república-bolivariana"}, {"valor": 26, "palabra": "esequibo-esequibo-venezuela"}, {"valor": 26, "palabra": "presidente-guyana-irfaan"}, {"valor": 26, "palabra": "maduro-moviliza-ejército"}, {"valor": 26, "palabra": "moviliza-ejército-anuncia"}, {"valor": 26, "palabra": "ratificamos-venezuela-esequibo"}, {"valor": 24, "palabra": "venezuela-nicolás-maduro"}, {"valor": 24, "palabra": "guyana-maduro-moviliza"}, {"valor": 24, "palabra": "venezuela-esequibo-esequibo"}, {"valor": 22, "palabra": "esequibo-venezuela-guyana"}, {"valor": 22, "palabra": "nuestro-venezuela-esequibo"}, {"valor": 22, "palabra": "nuestra-ratificamos-venezuela"}, {"valor": 21, "palabra": "bolivariana-venezuela-esequibo"}, {"valor": 21, "palabra": "esequibo-seguirá-siendo"}, {"valor": 21, "palabra": "anuncia-anexión-esequibo"}, {"valor": 21, "palabra": "esequibo-nuestro-esequibo"}]}}