{"2023-12-05-2023-12-05": {"VEN - Referendo Guyana - TW": [{"valor": 1569, "palabra": "venezuela"}, {"valor": 1349, "palabra": "esequibo"}, {"valor": 899, "palabra": "guyana"}, {"valor": 688, "palabra": "referéndum"}, {"valor": 598, "palabra": "referendo"}, {"valor": 416, "palabra": "consultivo"}, {"valor": 371, "palabra": "maduro"}, {"valor": 222, "palabra": "pueblo"}, {"valor": 214, "palabra": "territorio"}, {"valor": 195, "palabra": "estado"}, {"valor": 183, "palabra": "nuestro"}, {"valor": 179, "palabra": "presidente"}, {"valor": 171, "palabra": "disputa"}, {"valor": 158, "palabra": "venezolano"}, {"valor": 139, "palabra": "millones"}, {"valor": 133, "palabra": "declaraciones"}, {"valor": 131, "palabra": "rechaza"}, {"valor": 127, "palabra": "defensa"}, {"valor": 127, "palabra": "gobierno"}, {"valor": 119, "palabra": "venezolanos"}, {"valor": 119, "palabra": "intromisión"}, {"valor": 116, "palabra": "departamento"}, {"valor": 108, "palabra": "portavoz"}, {"valor": 107, "palabra": "resultados"}, {"valor": 102, "palabra": "vinculante"}, {"valor": 94, "palabra": "porque"}, {"valor": 85, "palabra": "nuestra"}, {"valor": 82, "palabra": "régimen"}, {"valor": 77, "palabra": "diciembre"}, {"valor": 77, "palabra": "participación"}, {"valor": 74, "palabra": "nicolás"}, {"valor": 70, "palabra": "guayana"}, {"valor": 70, "palabra": "ejercicio"}, {"valor": 69, "palabra": "nacional"}, {"valor": 65, "palabra": "contra"}, {"valor": 64, "palabra": "referendum"}, {"valor": 64, "palabra": "victoria"}, {"valor": 63, "palabra": "territorial"}, {"valor": 63, "palabra": "patria"}, {"valor": 63, "palabra": "unidos"}], "VEN - Nicolás Maduro - TW": [{"valor": 672, "palabra": "presidente"}, {"valor": 576, "palabra": "maduro"}, {"valor": 546, "palabra": "venezuela"}, {"valor": 307, "palabra": "nicolás"}, {"valor": 273, "palabra": "esequibo"}, {"valor": 270, "palabra": "pueblo"}, {"valor": 187, "palabra": "nuestro"}, {"valor": 163, "palabra": "guyana"}, {"valor": 133, "palabra": "referéndum"}, {"valor": 127, "palabra": "consultivo"}, {"valor": 126, "palabra": "nuestra"}, {"valor": 111, "palabra": "referendo"}, {"valor": 111, "palabra": "millones"}, {"valor": 106, "palabra": "venezolano"}, {"valor": 106, "palabra": "contra"}, {"valor": 103, "palabra": "siempre"}, {"valor": 97, "palabra": "patria"}, {"valor": 94, "palabra": "gobierno"}, {"valor": 90, "palabra": "porque"}, {"valor": 87, "palabra": "estado"}, {"valor": 82, "palabra": "cuando"}, {"valor": 73, "palabra": "venezolanos"}, {"valor": 73, "palabra": "territorio"}, {"valor": 69, "palabra": "victoria"}, {"valor": 69, "palabra": "resultados"}, {"valor": 68, "palabra": "diciembre"}, {"valor": 66, "palabra": "venceremos"}, {"valor": 64, "palabra": "municipio"}, {"valor": 63, "palabra": "nacional"}, {"valor": 58, "palabra": "caribe"}, {"valor": 56, "palabra": "vinculante"}, {"valor": 55, "palabra": "defensa"}, {"valor": 54, "palabra": "gracias"}, {"valor": 53, "palabra": "chávez"}, {"valor": 50, "palabra": "verdad"}, {"valor": 50, "palabra": "unidos"}, {"valor": 48, "palabra": "guayana"}, {"valor": 48, "palabra": "primitivo"}, {"valor": 48, "palabra": "manipulación"}, {"valor": 47, "palabra": "tienen"}]}}