{"2023-12-09-2023-12-09": {"VEN - Nicolás Maduro - TW": [{"valor": 35, "palabra": "presidente-nicolás-maduro"}, {"valor": 22, "palabra": "acompaña-marcha-pueblo"}, {"valor": 22, "palabra": "marcha-pueblo-respaldo"}, {"valor": 22, "palabra": "pueblo-respaldo-acción"}, {"valor": 21, "palabra": "república-bolivariana-venezuela"}, {"valor": 21, "palabra": "respaldo-acción-defensa"}, {"valor": 21, "palabra": "acción-defensa-territorio"}, {"valor": 21, "palabra": "defensa-territorio-esequibo"}, {"valor": 18, "palabra": "nicolás-maduro-decretos"}, {"valor": 13, "palabra": "venezuela-nicolás-maduro"}, {"valor": 12, "palabra": "guyana-desescalar-conflicto"}, {"valor": 11, "palabra": "venezuela-guyana-desescalar"}, {"valor": 10, "palabra": "concepción-palacios-blanco"}, {"valor": 9, "palabra": "maduro-decretos-avanzar"}, {"valor": 9, "palabra": "decretos-avanzar-anexión"}, {"valor": 8, "palabra": "nicolás-maduro-primitivo"}, {"valor": 8, "palabra": "maduro-primitivo-cedeño"}, {"valor": 8, "palabra": "people-fearful-guyana"}, {"valor": 8, "palabra": "fearful-guyana-venezuelan"}, {"valor": 8, "palabra": "guyana-venezuelan-president"}, {"valor": 8, "palabra": "venezuelan-president-nicolás"}, {"valor": 8, "palabra": "president-nicolás-maduro"}, {"valor": 8, "palabra": "presidente-gustavo-venezuela"}, {"valor": 8, "palabra": "gustavo-venezuela-guyana"}, {"valor": 8, "palabra": "medidas-defensa-esequibo"}, {"valor": 8, "palabra": "oficial-república-bolivariana"}, {"valor": 7, "palabra": "lealtad-comandante-chávez"}, {"valor": 7, "palabra": "régimen-nicolás-maduro"}, {"valor": 7, "palabra": "presidente-maduro-traidores"}, {"valor": 7, "palabra": "maduro-traidores-patria"}], "VEN - Referendo Guyana - TW": [{"valor": 118, "palabra": "república-bolivariana-venezuela"}, {"valor": 48, "palabra": "espero-entienda-venezuela"}, {"valor": 48, "palabra": "entienda-venezuela-territorio"}, {"valor": 48, "palabra": "venezuela-territorio-pelear"}, {"valor": 48, "palabra": "territorio-pelear-pelearemos"}, {"valor": 48, "palabra": "pelear-pelearemos-nuestra"}, {"valor": 48, "palabra": "pelearemos-nuestra-patria"}, {"valor": 48, "palabra": "nuestra-patria-moriremos"}, {"valor": 48, "palabra": "patria-moriremos-centímetro"}, {"valor": 48, "palabra": "moriremos-centímetro-nuestro"}, {"valor": 48, "palabra": "centímetro-nuestro-esequibo"}, {"valor": 48, "palabra": "nuestro-esequibo-invasores"}, {"valor": 48, "palabra": "esequibo-invasores-guyaneses"}, {"valor": 31, "palabra": "rincón-patria-llevamos"}, {"valor": 31, "palabra": "patria-llevamos-república"}, {"valor": 31, "palabra": "llevamos-república-bolivariana"}, {"valor": 31, "palabra": "bolivariana-venezuela-soldados"}, {"valor": 31, "palabra": "venezuela-soldados-nuestra"}, {"valor": 31, "palabra": "soldados-nuestra-desplegados"}, {"valor": 31, "palabra": "nuestra-desplegados-defensa"}, {"valor": 31, "palabra": "desplegados-defensa-soberanía"}, {"valor": 31, "palabra": "defensa-soberanía-nacional"}, {"valor": 30, "palabra": "venezuela-esequibo-venezuela"}, {"valor": 29, "palabra": "esequibo-patria-rincón"}, {"valor": 29, "palabra": "patria-rincón-patria"}, {"valor": 28, "palabra": "nuestra-guayana-esequiba"}, {"valor": 25, "palabra": "nuestro-república-bolivariana"}, {"valor": 24, "palabra": "capitanía-general-venezuela"}, {"valor": 23, "palabra": "venezuela-guyana-esequibo"}, {"valor": 22, "palabra": "conflicto-venezuela-guyana"}]}}