{"2023-12-09-2023-12-09": [{"Influencer": "petrogustavo", "Centralidad": 44.6}, {"Influencer": "juanmanuelgalan", "Centralidad": 39.45}, {"Influencer": "AlvaroLeyva", "Centralidad": 37.61}, {"Influencer": "watchsingle", "Centralidad": 16.07}, {"Influencer": "EleccionesVzla2", "Centralidad": 15.55}, {"Influencer": "avis_ink", "Centralidad": 15.32}, {"Influencer": "rafaelm07327900", "Centralidad": 15.31}, {"Influencer": "gregorioconte", "Centralidad": 15.08}, {"Influencer": "Hen_Ser", "Centralidad": 15.08}, {"Influencer": "jurago76", "Centralidad": 15.08}, {"Influencer": "IbzanCardenasG", "Centralidad": 15.08}, {"Influencer": "Dougls420", "Centralidad": 15.08}, {"Influencer": "fmotisi", "Centralidad": 15.08}, {"Influencer": "JosMoron4", "Centralidad": 15.08}, {"Influencer": "Ruben2207", "Centralidad": 15.08}]}