{"2023-12-03-2023-12-03": {"VEN - Nicolás Maduro - TW": [{"valor": 831, "palabra": "esequibo-nuestro"}, {"valor": 747, "palabra": "nicolás-maduro"}, {"valor": 642, "palabra": "nuestro-esequibo"}, {"valor": 478, "palabra": "referéndum-consultivo"}, {"valor": 352, "palabra": "guayana-esequiba"}, {"valor": 339, "palabra": "nuestra-patria"}, {"valor": 327, "palabra": "defensa-nuestro"}, {"valor": 314, "palabra": "nuestro-territorio"}, {"valor": 309, "palabra": "venezuela-esequibo"}, {"valor": 300, "palabra": "esequibo-venezuela"}, {"valor": 256, "palabra": "defensa-esequibo"}, {"valor": 240, "palabra": "presidente-maduro"}, {"valor": 228, "palabra": "consultivo-defensa"}, {"valor": 219, "palabra": "referendo-consultivo"}, {"valor": 210, "palabra": "territorio-esequibo"}, {"valor": 205, "palabra": "nuestra-soberanía"}, {"valor": 197, "palabra": "pueblo-venezolano"}, {"valor": 195, "palabra": "ejerció-derecho"}, {"valor": 188, "palabra": "defensa-nuestra"}, {"valor": 186, "palabra": "presidente-venezuela"}, {"valor": 160, "palabra": "presidente-guyana"}, {"valor": 156, "palabra": "presidente-nicolás"}, {"valor": 149, "palabra": "nuestro-presidente"}, {"valor": 142, "palabra": "derecho-referéndum"}, {"valor": 133, "palabra": "ejerce-derecho"}, {"valor": 129, "palabra": "consultivo-esequibo"}, {"valor": 125, "palabra": "defender-nuestro"}, {"valor": 122, "palabra": "nuestra-guayana"}, {"valor": 119, "palabra": "esequibo-presidente"}, {"valor": 114, "palabra": "ejercer-derecho"}], "VEN - Referendo Guyana - TW": [{"valor": 2085, "palabra": "referéndum-consultivo"}, {"valor": 1777, "palabra": "esequibo-venezuela"}, {"valor": 1522, "palabra": "venezuela-esequibo"}, {"valor": 1047, "palabra": "esequibo-nuestro"}, {"valor": 988, "palabra": "referendo-consultivo"}, {"valor": 852, "palabra": "consultivo-esequibo"}, {"valor": 813, "palabra": "nuestro-esequibo"}, {"valor": 752, "palabra": "consultivo-defensa"}, {"valor": 707, "palabra": "territorio-esequibo"}, {"valor": 672, "palabra": "defensa-esequibo"}, {"valor": 618, "palabra": "referendo-esequibo"}, {"valor": 565, "palabra": "guayana-esequiba"}, {"valor": 534, "palabra": "referéndum-esequibo"}, {"valor": 400, "palabra": "defensa-nuestro"}, {"valor": 393, "palabra": "nuestro-territorio"}, {"valor": 389, "palabra": "derecho-referéndum"}, {"valor": 363, "palabra": "venezuela-guyana"}, {"valor": 356, "palabra": "ejerció-derecho"}, {"valor": 308, "palabra": "nicolás-maduro"}, {"valor": 273, "palabra": "centros-votación"}, {"valor": 271, "palabra": "venezuela-venezuela"}, {"valor": 257, "palabra": "defensa-territorio"}, {"valor": 244, "palabra": "guyana-venezuela"}, {"valor": 242, "palabra": "esequibo-esequibo"}, {"valor": 236, "palabra": "pueblo-venezolano"}, {"valor": 226, "palabra": "nuestro-venezuela"}, {"valor": 214, "palabra": "nuestra-patria"}, {"valor": 190, "palabra": "presidente-guyana"}, {"valor": 188, "palabra": "ejercer-derecho"}, {"valor": 180, "palabra": "nuestra-soberanía"}]}}