{"2023-11-24-2023-11-24": [{"Influencer": "dhernandezlarez", "Centralidad": 12.13}, {"Influencer": "VTVcanal8", "Centralidad": 11.97}, {"Influencer": "AntroCanal", "Centralidad": 9.41}, {"Influencer": "polianalitica", "Centralidad": 9.35}, {"Influencer": "CaroCarreroCC", "Centralidad": 9.27}, {"Influencer": "vladimirpadrino", "Centralidad": 8.96}, {"Influencer": "Mente_Ordenada", "Centralidad": 8.91}, {"Influencer": "jaarreaza", "Centralidad": 5.1}, {"Influencer": "Mippcivzla", "Centralidad": 4.63}, {"Influencer": "AleFleming", "Centralidad": 4.27}, {"Influencer": "PrensaFANB", "Centralidad": 4.25}, {"Influencer": "jesusmedinae", "Centralidad": 4.19}, {"Influencer": "MariaCorinaYA", "Centralidad": 4.03}, {"Influencer": "dcabellor", "Centralidad": 4.02}, {"Influencer": "GNB_tachira", "Centralidad": 3.41}], "2023-11-25-2023-11-25": [{"Influencer": "vladimirpadrino", "Centralidad": 12.56}, {"Influencer": "delcyrodriguezv", "Centralidad": 12.27}, {"Influencer": "aecarri", "Centralidad": 10.79}, {"Influencer": "Umbv_Fanb", "Centralidad": 7.05}, {"Influencer": "LESCAM07", "Centralidad": 6.54}, {"Influencer": "sergioobregon1", "Centralidad": 6.43}, {"Influencer": "AntroCanal", "Centralidad": 6.25}, {"Influencer": "jaarreaza", "Centralidad": 5.79}, {"Influencer": "GnbGaranteDePaz", "Centralidad": 4.98}, {"Influencer": "WilmarWilmarlub", "Centralidad": 4.49}, {"Influencer": "cperezlavatelli", "Centralidad": 4.36}, {"Influencer": "dcabellor", "Centralidad": 4.02}, {"Influencer": "graywolf787", "Centralidad": 3.84}, {"Influencer": "eddyleon", "Centralidad": 3.55}, {"Influencer": "polianalitica", "Centralidad": 3.5}]}