{"2023-12-08-2023-12-08": {"VEN - Referendo Guyana - TW": [{"valor": 583, "palabra": "esequibo-venezuela"}, {"valor": 573, "palabra": "venezuela-guyana"}, {"valor": 467, "palabra": "venezuela-esequibo"}, {"valor": 200, "palabra": "guyana-venezuela"}, {"valor": 188, "palabra": "territorio-esequibo"}, {"valor": 155, "palabra": "guayana-esequiba"}, {"valor": 135, "palabra": "esequibo-nuestro"}, {"valor": 111, "palabra": "estados-unidos"}, {"valor": 106, "palabra": "venezuela-venezuela"}, {"valor": 106, "palabra": "guyana-esequibo"}, {"valor": 97, "palabra": "ejercicios-militares"}, {"valor": 97, "palabra": "militares-guyana"}, {"valor": 87, "palabra": "disputa-venezuela"}, {"valor": 84, "palabra": "disputa-territorial"}, {"valor": 77, "palabra": "territorial-venezuela"}, {"valor": 76, "palabra": "bolivariana-venezuela"}, {"valor": 75, "palabra": "consejo-seguridad"}, {"valor": 75, "palabra": "república-bolivariana"}, {"valor": 73, "palabra": "acuerdo-ginebra"}, {"valor": 72, "palabra": "nicolás-maduro"}, {"valor": 71, "palabra": "nuestro-esequibo"}, {"valor": 70, "palabra": "conflicto-venezuela"}, {"valor": 69, "palabra": "nuestro-territorio"}, {"valor": 68, "palabra": "venezuela-territorio"}, {"valor": 66, "palabra": "tensión-venezuela"}, {"valor": 65, "palabra": "referéndum-consultivo"}, {"valor": 63, "palabra": "referendo-esequibo"}, {"valor": 59, "palabra": "solución-pacífica"}, {"valor": 57, "palabra": "frontera-venezuela"}, {"valor": 53, "palabra": "contra-venezuela"}], "VEN - Nicolás Maduro - TW": [{"valor": 401, "palabra": "nicolás-maduro"}, {"valor": 116, "palabra": "guayana-esequiba"}, {"valor": 95, "palabra": "presidente-guyana"}, {"valor": 82, "palabra": "esequibo-nuestro"}, {"valor": 66, "palabra": "comandante-chávez"}, {"valor": 62, "palabra": "presidente-nicolás"}, {"valor": 58, "palabra": "presidente-venezuela"}, {"valor": 55, "palabra": "presidente-maduro"}, {"valor": 55, "palabra": "nuestro-presidente"}, {"valor": 55, "palabra": "territorio-esequibo"}, {"valor": 53, "palabra": "nicolas-maduro"}, {"valor": 52, "palabra": "maduro-esequibo"}, {"valor": 50, "palabra": "misión-vivienda"}, {"valor": 49, "palabra": "pueblo-venezolano"}, {"valor": 46, "palabra": "lealtad-comandante"}, {"valor": 45, "palabra": "unidad-batalla"}, {"valor": 44, "palabra": "congreso-pedagógico"}, {"valor": 44, "palabra": "batalla-victoria"}, {"valor": 41, "palabra": "estados-unidos"}, {"valor": 40, "palabra": "nuestro-pueblo"}, {"valor": 39, "palabra": "nuestro-esequibo"}, {"valor": 39, "palabra": "vivienda-venezuela"}, {"valor": 39, "palabra": "bolivariana-venezuela"}, {"valor": 39, "palabra": "policía-nacional"}, {"valor": 36, "palabra": "venezuela-presidente"}, {"valor": 36, "palabra": "nuestro-comandante"}, {"valor": 35, "palabra": "esequibo-venezuela"}, {"valor": 34, "palabra": "nacional-bolivariana"}, {"valor": 33, "palabra": "república-bolivariana"}, {"valor": 32, "palabra": "advertencia-presidente"}]}}