{"2023-12-08-2023-12-08": {"VEN - Referendo Guyana - TW": [{"valor": 480, "palabra": "esequibo-venezuela"}, {"valor": 407, "palabra": "venezuela-esequibo"}, {"valor": 385, "palabra": "venezuela-guyana"}, {"valor": 146, "palabra": "territorio-esequibo"}, {"valor": 144, "palabra": "guyana-venezuela"}, {"valor": 126, "palabra": "guayana-esequiba"}, {"valor": 121, "palabra": "esequibo-nuestro"}, {"valor": 90, "palabra": "venezuela-venezuela"}, {"valor": 89, "palabra": "militares-guyana"}, {"valor": 88, "palabra": "estados-unidos"}, {"valor": 87, "palabra": "ejercicios-militares"}, {"valor": 79, "palabra": "guyana-esequibo"}, {"valor": 65, "palabra": "república-bolivariana"}, {"valor": 65, "palabra": "bolivariana-venezuela"}, {"valor": 64, "palabra": "nuestro-territorio"}, {"valor": 61, "palabra": "disputa-venezuela"}, {"valor": 61, "palabra": "tensión-venezuela"}, {"valor": 59, "palabra": "consejo-seguridad"}, {"valor": 54, "palabra": "acuerdo-ginebra"}, {"valor": 53, "palabra": "territorial-venezuela"}, {"valor": 53, "palabra": "venezuela-territorio"}, {"valor": 52, "palabra": "conflicto-venezuela"}, {"valor": 52, "palabra": "nicolás-maduro"}, {"valor": 52, "palabra": "nuestro-esequibo"}, {"valor": 50, "palabra": "disputa-territorial"}, {"valor": 49, "palabra": "frontera-venezuela"}, {"valor": 46, "palabra": "referendo-esequibo"}, {"valor": 45, "palabra": "referéndum-consultivo"}, {"valor": 44, "palabra": "esequibo-esequibo"}, {"valor": 43, "palabra": "nuestro-venezuela"}], "VEN - Nicolás Maduro - TW": [{"valor": 321, "palabra": "nicolás-maduro"}, {"valor": 87, "palabra": "guayana-esequiba"}, {"valor": 87, "palabra": "presidente-guyana"}, {"valor": 79, "palabra": "esequibo-nuestro"}, {"valor": 51, "palabra": "maduro-esequibo"}, {"valor": 50, "palabra": "presidente-maduro"}, {"valor": 47, "palabra": "presidente-venezuela"}, {"valor": 45, "palabra": "presidente-nicolás"}, {"valor": 44, "palabra": "misión-vivienda"}, {"valor": 41, "palabra": "comandante-chávez"}, {"valor": 40, "palabra": "nicolas-maduro"}, {"valor": 39, "palabra": "territorio-esequibo"}, {"valor": 35, "palabra": "estados-unidos"}, {"valor": 35, "palabra": "nuestro-esequibo"}, {"valor": 35, "palabra": "nuestro-presidente"}, {"valor": 35, "palabra": "nuestro-pueblo"}, {"valor": 35, "palabra": "pueblo-venezolano"}, {"valor": 33, "palabra": "venezuela-presidente"}, {"valor": 33, "palabra": "vivienda-venezuela"}, {"valor": 32, "palabra": "advertencia-presidente"}, {"valor": 32, "palabra": "guyana-invasión"}, {"valor": 32, "palabra": "invasión-anunció"}, {"valor": 32, "palabra": "anunció-nicolás"}, {"valor": 31, "palabra": "bolivariana-venezuela"}, {"valor": 31, "palabra": "policía-nacional"}, {"valor": 27, "palabra": "esequibo-venezuela"}, {"valor": 27, "palabra": "unidad-batalla"}, {"valor": 27, "palabra": "batalla-victoria"}, {"valor": 27, "palabra": "lealtad-comandante"}, {"valor": 26, "palabra": "corina-machado"}]}}