{"2023-12-10-2023-12-10": {"VEN - Nicolás Maduro - TW": [{"valor": 1244, "palabra": "presidente"}, {"valor": 1079, "palabra": "venezuela"}, {"valor": 985, "palabra": "maduro"}, {"valor": 508, "palabra": "nicolás"}, {"valor": 489, "palabra": "guyana"}, {"valor": 450, "palabra": "nuestro"}, {"valor": 413, "palabra": "esequibo"}, {"valor": 359, "palabra": "pueblo"}, {"valor": 173, "palabra": "cuando"}, {"valor": 172, "palabra": "nuestra"}, {"valor": 157, "palabra": "territorio"}, {"valor": 150, "palabra": "porque"}, {"valor": 149, "palabra": "chávez"}, {"valor": 148, "palabra": "argentina"}, {"valor": 147, "palabra": "patria"}, {"valor": 146, "palabra": "gobierno"}, {"valor": 138, "palabra": "venezolano"}, {"valor": 136, "palabra": "guayana"}, {"valor": 124, "palabra": "reunión"}, {"valor": 122, "palabra": "siempre"}, {"valor": 120, "palabra": "esequiba"}, {"valor": 116, "palabra": "contra"}, {"valor": 115, "palabra": "derechos"}, {"valor": 113, "palabra": "estado"}, {"valor": 110, "palabra": "venezolanos"}, {"valor": 108, "palabra": "diciembre"}, {"valor": 95, "palabra": "venceremos"}, {"valor": 94, "palabra": "defensa"}, {"valor": 92, "palabra": "irfaan"}, {"valor": 92, "palabra": "gracias"}, {"valor": 89, "palabra": "nicolas"}, {"valor": 82, "palabra": "tienen"}, {"valor": 82, "palabra": "diálogo"}, {"valor": 82, "palabra": "javier"}, {"valor": 81, "palabra": "guerra"}, {"valor": 81, "palabra": "general"}, {"valor": 80, "palabra": "humanos"}, {"valor": 75, "palabra": "dictador"}, {"valor": 74, "palabra": "seguimos"}, {"valor": 74, "palabra": "libertad"}], "VEN - Referendo Guyana - TW": [{"valor": 2098, "palabra": "venezuela"}, {"valor": 1309, "palabra": "guyana"}, {"valor": 1306, "palabra": "esequibo"}, {"valor": 298, "palabra": "maduro"}, {"valor": 241, "palabra": "presidente"}, {"valor": 239, "palabra": "territorio"}, {"valor": 232, "palabra": "nuestro"}, {"valor": 210, "palabra": "reunión"}, {"valor": 203, "palabra": "referéndum"}, {"valor": 167, "palabra": "disputa"}, {"valor": 155, "palabra": "presidentes"}, {"valor": 152, "palabra": "diciembre"}, {"valor": 131, "palabra": "pueblo"}, {"valor": 123, "palabra": "territorial"}, {"valor": 111, "palabra": "conflicto"}, {"valor": 110, "palabra": "diálogo"}, {"valor": 107, "palabra": "gobierno"}, {"valor": 104, "palabra": "vicente"}, {"valor": 103, "palabra": "venezolano"}, {"valor": 101, "palabra": "reunirán"}, {"valor": 99, "palabra": "acuerdo"}, {"valor": 95, "palabra": "caricom"}, {"valor": 91, "palabra": "granadinas"}, {"valor": 91, "palabra": "referendo"}, {"valor": 90, "palabra": "nicolás"}, {"valor": 88, "palabra": "guerra"}, {"valor": 83, "palabra": "estado"}, {"valor": 83, "palabra": "porque"}, {"valor": 79, "palabra": "nuestra"}, {"valor": 74, "palabra": "siempre"}, {"valor": 73, "palabra": "próximo"}, {"valor": 73, "palabra": "jueves"}, {"valor": 71, "palabra": "petróleo"}, {"valor": 70, "palabra": "consultivo"}, {"valor": 67, "palabra": "guayana"}, {"valor": 67, "palabra": "contra"}, {"valor": 66, "palabra": "controversia"}, {"valor": 66, "palabra": "venezolanos"}, {"valor": 65, "palabra": "república"}, {"valor": 64, "palabra": "esequiba"}]}}