{"2023-11-15-2023-11-15": {"VEN - Referendo Guyana - TW": [{"valor": 2529, "palabra": "esequibo-venezuela"}, {"valor": 2108, "palabra": "venezuela-esequibo"}, {"valor": 1109, "palabra": "esequibo-nuestro"}, {"valor": 857, "palabra": "nuestro-esequibo"}, {"valor": 806, "palabra": "referéndum-consultivo"}, {"valor": 754, "palabra": "territorio-esequibo"}, {"valor": 567, "palabra": "nuestro-territorio"}, {"valor": 533, "palabra": "esequibo-esequibo"}, {"valor": 460, "palabra": "defensa-esequibo"}, {"valor": 436, "palabra": "venezuela-venezuela"}, {"valor": 391, "palabra": "defensa-nuestro"}, {"valor": 371, "palabra": "nuestro-venezuela"}, {"valor": 338, "palabra": "referendo-consultivo"}, {"valor": 304, "palabra": "guayana-esequiba"}, {"valor": 303, "palabra": "venezuela-defensa"}, {"valor": 265, "palabra": "referendo-esequibo"}, {"valor": 260, "palabra": "campaña-venezuela"}, {"valor": 246, "palabra": "esequibo-pertenece"}, {"valor": 240, "palabra": "consultivo-esequibo"}, {"valor": 216, "palabra": "consultivo-defensa"}, {"valor": 214, "palabra": "referéndum-esequibo"}, {"valor": 209, "palabra": "nuestra-patria"}, {"valor": 188, "palabra": "venezuela-guyana"}, {"valor": 187, "palabra": "nuestra-venezuela"}, {"valor": 174, "palabra": "venezuela-nuestro"}, {"valor": 145, "palabra": "patria-venezuela"}, {"valor": 145, "palabra": "defender-nuestro"}, {"valor": 143, "palabra": "internacional-justicia"}, {"valor": 137, "palabra": "pueblo-venezolano"}, {"valor": 133, "palabra": "nuestra-soberanía"}], "VEN - Nicolás Maduro - TW": [{"valor": 614, "palabra": "nicolás-maduro"}, {"valor": 515, "palabra": "esequibo-nuestro"}, {"valor": 253, "palabra": "nuestro-esequibo"}, {"valor": 236, "palabra": "nuestro-territorio"}, {"valor": 179, "palabra": "guayana-esequiba"}, {"valor": 130, "palabra": "nuestro-pueblo"}, {"valor": 121, "palabra": "presidente-maduro"}, {"valor": 113, "palabra": "territorio-esequibo"}, {"valor": 112, "palabra": "nicolas-maduro"}, {"valor": 111, "palabra": "pueblo-venezolano"}, {"valor": 109, "palabra": "presidente-venezuela"}, {"valor": 108, "palabra": "defensa-nuestro"}, {"valor": 98, "palabra": "presidente-nicolás"}, {"valor": 84, "palabra": "relaciones-diplomáticas"}, {"valor": 82, "palabra": "nuestra-patria"}, {"valor": 80, "palabra": "nuestro-presidente"}, {"valor": 65, "palabra": "esequibo-venezuela"}, {"valor": 61, "palabra": "defensa-esequibo"}, {"valor": 58, "palabra": "esequibo-pertenece"}, {"valor": 56, "palabra": "venezuela-presidente"}, {"valor": 56, "palabra": "venezuela-esequibo"}, {"valor": 51, "palabra": "territorio-venezolano"}, {"valor": 50, "palabra": "maduro-presidente"}, {"valor": 50, "palabra": "diplomáticas-consulares"}, {"valor": 46, "palabra": "defender-nuestro"}, {"valor": 41, "palabra": "nuestra-guayana"}, {"valor": 41, "palabra": "guerra-económica"}, {"valor": 40, "palabra": "nuestro-venceremos"}, {"valor": 38, "palabra": "maduro-venezuela"}, {"valor": 38, "palabra": "defenderemos-nuestro"}]}, "2023-11-16-2023-11-16": {"VEN - Referendo Guyana - TW": [{"valor": 229, "palabra": "esequibo-venezuela"}, {"valor": 226, "palabra": "venezuela-esequibo"}, {"valor": 163, "palabra": "esequibo-nuestro"}, {"valor": 119, "palabra": "nuestro-esequibo"}, {"valor": 77, "palabra": "referéndum-consultivo"}, {"valor": 75, "palabra": "territorio-esequibo"}, {"valor": 55, "palabra": "buenos-venezuela"}, {"valor": 50, "palabra": "defensa-esequibo"}, {"valor": 48, "palabra": "esequibo-esequibo"}, {"valor": 48, "palabra": "venezuela-venezuela"}, {"valor": 47, "palabra": "nuestro-territorio"}, {"valor": 39, "palabra": "referendo-esequibo"}, {"valor": 38, "palabra": "campaña-venezuela"}, {"valor": 37, "palabra": "nuestro-venezuela"}, {"valor": 36, "palabra": "guayana-esequiba"}, {"valor": 34, "palabra": "referendo-consultivo"}, {"valor": 34, "palabra": "referéndum-esequibo"}, {"valor": 33, "palabra": "esequibo-buenos"}, {"valor": 32, "palabra": "consultivo-esequibo"}, {"valor": 27, "palabra": "defensa-nuestro"}, {"valor": 26, "palabra": "venezuela-guyana"}, {"valor": 25, "palabra": "pueblo-venezolano"}, {"valor": 24, "palabra": "venezuela-diciembre"}, {"valor": 24, "palabra": "venezuela-pueblo"}, {"valor": 23, "palabra": "nuestra-patria"}, {"valor": 23, "palabra": "internacional-justicia"}, {"valor": 22, "palabra": "patria-venezuela"}, {"valor": 22, "palabra": "esequibo-diciembre"}, {"valor": 19, "palabra": "próximo-diciembre"}, {"valor": 19, "palabra": "diciembre-nuestro"}], "VEN - Nicolás Maduro - TW": [{"valor": 82, "palabra": "nicolás-maduro"}, {"valor": 51, "palabra": "esequibo-nuestro"}, {"valor": 39, "palabra": "presidente-maduro"}, {"valor": 25, "palabra": "nuestro-territorio"}, {"valor": 22, "palabra": "nicolas-maduro"}, {"valor": 21, "palabra": "pueblo-venezolano"}, {"valor": 19, "palabra": "guayana-esequiba"}, {"valor": 18, "palabra": "laguito-círculo"}, {"valor": 18, "palabra": "círculo-militar"}, {"valor": 18, "palabra": "militar-caracas"}, {"valor": 18, "palabra": "caracas-información"}, {"valor": 14, "palabra": "presidente-venezuela"}, {"valor": 14, "palabra": "nuestro-esequibo"}, {"valor": 10, "palabra": "territorio-esequibo"}, {"valor": 9, "palabra": "encuentro-venezolanos"}, {"valor": 9, "palabra": "venezuela-presidente"}, {"valor": 8, "palabra": "defensa-nuestro"}, {"valor": 8, "palabra": "nuestro-pueblo"}, {"valor": 8, "palabra": "territorio-venezolano"}, {"valor": 8, "palabra": "esequibo-esequibo"}, {"valor": 8, "palabra": "venezolanos-esequibo"}, {"valor": 8, "palabra": "nuestro-venezuela"}, {"valor": 8, "palabra": "creación-instituto"}, {"valor": 8, "palabra": "instituto-nacional"}, {"valor": 8, "palabra": "nacional-asuntos"}, {"valor": 8, "palabra": "asuntos-religiosos"}, {"valor": 8, "palabra": "religiosos-cultos"}, {"valor": 8, "palabra": "cultos-venezuela"}, {"valor": 8, "palabra": "nuestro-presidente"}, {"valor": 8, "palabra": "maduro-venezuela"}]}}