{"2023-11-13-2023-11-13": {"VEN - Referendo Guyana - TW": [{"valor": 1903, "palabra": "esequibo-venezuela"}, {"valor": 1751, "palabra": "venezuela-esequibo"}, {"valor": 897, "palabra": "esequibo-nuestro"}, {"valor": 791, "palabra": "referéndum-consultivo"}, {"valor": 653, "palabra": "nuestro-esequibo"}, {"valor": 599, "palabra": "territorio-esequibo"}, {"valor": 431, "palabra": "esequibo-esequibo"}, {"valor": 391, "palabra": "nuestro-territorio"}, {"valor": 360, "palabra": "defensa-esequibo"}, {"valor": 355, "palabra": "venezuela-venezuela"}, {"valor": 286, "palabra": "defensa-nuestro"}, {"valor": 278, "palabra": "nuestro-venezuela"}, {"valor": 218, "palabra": "nuestra-patria"}, {"valor": 217, "palabra": "guayana-esequiba"}, {"valor": 206, "palabra": "venezuela-defensa"}, {"valor": 202, "palabra": "consultivo-esequibo"}, {"valor": 193, "palabra": "referendo-consultivo"}, {"valor": 193, "palabra": "consultivo-defensa"}, {"valor": 184, "palabra": "referendo-esequibo"}, {"valor": 171, "palabra": "patria-venezuela"}, {"valor": 166, "palabra": "referéndum-esequibo"}, {"valor": 160, "palabra": "defensa-territorio"}, {"valor": 155, "palabra": "esequibo-pertenece"}, {"valor": 131, "palabra": "nuestra-soberanía"}, {"valor": 130, "palabra": "campaña-venezuela"}, {"valor": 122, "palabra": "plataforma-unitaria"}, {"valor": 122, "palabra": "venezuela-nuestro"}, {"valor": 105, "palabra": "esequibo-nuestra"}, {"valor": 103, "palabra": "territorio-nacional"}, {"valor": 102, "palabra": "defender-nuestro"}], "VEN - Nicolás Maduro - TW": [{"valor": 570, "palabra": "nicolás-maduro"}, {"valor": 268, "palabra": "esequibo-nuestro"}, {"valor": 136, "palabra": "nuestro-esequibo"}, {"valor": 134, "palabra": "nuestro-presidente"}, {"valor": 119, "palabra": "nicolas-maduro"}, {"valor": 114, "palabra": "presidente-maduro"}, {"valor": 112, "palabra": "presidente-nicolás"}, {"valor": 105, "palabra": "nuestro-territorio"}, {"valor": 95, "palabra": "nuestra-patria"}, {"valor": 85, "palabra": "presidente-venezuela"}, {"valor": 85, "palabra": "guayana-esequiba"}, {"valor": 79, "palabra": "sanciones-contra"}, {"valor": 77, "palabra": "defensa-nuestro"}, {"valor": 73, "palabra": "programa-maduro"}, {"valor": 66, "palabra": "gobierno-nicolás"}, {"valor": 64, "palabra": "pueblo-venezolano"}, {"valor": 63, "palabra": "nuestro-pueblo"}, {"valor": 60, "palabra": "territorio-esequibo"}, {"valor": 58, "palabra": "defensa-esequibo"}, {"valor": 55, "palabra": "carlos-delgado"}, {"valor": 53, "palabra": "primitivo-cedeño"}, {"valor": 52, "palabra": "delgado-chalbaud"}, {"valor": 48, "palabra": "presidente-militar"}, {"valor": 46, "palabra": "república-bolivariana"}, {"valor": 46, "palabra": "misión-venezuela"}, {"valor": 46, "palabra": "militar-gobierno"}, {"valor": 45, "palabra": "bolivariana-venezuela"}, {"valor": 43, "palabra": "maduro-presidente"}, {"valor": 43, "palabra": "estados-unidos"}, {"valor": 42, "palabra": "maduro-primitivo"}]}, "2023-11-14-2023-11-14": {"VEN - Referendo Guyana - TW": [{"valor": 1339, "palabra": "esequibo-venezuela"}, {"valor": 1111, "palabra": "venezuela-esequibo"}, {"valor": 708, "palabra": "esequibo-nuestro"}, {"valor": 510, "palabra": "referéndum-consultivo"}, {"valor": 488, "palabra": "nuestro-esequibo"}, {"valor": 437, "palabra": "territorio-esequibo"}, {"valor": 266, "palabra": "nuestro-territorio"}, {"valor": 260, "palabra": "esequibo-esequibo"}, {"valor": 227, "palabra": "venezuela-venezuela"}, {"valor": 209, "palabra": "defensa-esequibo"}, {"valor": 208, "palabra": "defensa-nuestro"}, {"valor": 188, "palabra": "consultivo-esequibo"}, {"valor": 176, "palabra": "nuestro-venezuela"}, {"valor": 173, "palabra": "referendo-consultivo"}, {"valor": 173, "palabra": "guayana-esequiba"}, {"valor": 162, "palabra": "venezuela-defensa"}, {"valor": 158, "palabra": "nuestra-patria"}, {"valor": 154, "palabra": "referendo-esequibo"}, {"valor": 143, "palabra": "esequibo-pertenece"}, {"valor": 107, "palabra": "patria-venezuela"}, {"valor": 104, "palabra": "campaña-venezuela"}, {"valor": 104, "palabra": "referéndum-esequibo"}, {"valor": 101, "palabra": "internacional-justicia"}, {"valor": 99, "palabra": "pueblo-venezolano"}, {"valor": 98, "palabra": "venezuela-guyana"}, {"valor": 92, "palabra": "venezuela-nuestro"}, {"valor": 92, "palabra": "nuestra-venezuela"}, {"valor": 89, "palabra": "consultivo-defensa"}, {"valor": 87, "palabra": "acuerdo-ginebra"}, {"valor": 87, "palabra": "esequibo-nuestra"}], "VEN - Nicolás Maduro - TW": [{"valor": 360, "palabra": "nicolás-maduro"}, {"valor": 252, "palabra": "esequibo-nuestro"}, {"valor": 133, "palabra": "presidente-maduro"}, {"valor": 115, "palabra": "nuestro-esequibo"}, {"valor": 101, "palabra": "nuestro-territorio"}, {"valor": 80, "palabra": "cuerpo-diplomático"}, {"valor": 79, "palabra": "presidente-nicolás"}, {"valor": 78, "palabra": "guayana-esequiba"}, {"valor": 76, "palabra": "nuestra-patria"}, {"valor": 69, "palabra": "acreditado-exterior"}, {"valor": 69, "palabra": "presidente-venezuela"}, {"valor": 65, "palabra": "territorio-esequibo"}, {"valor": 58, "palabra": "nuestro-presidente"}, {"valor": 57, "palabra": "antonio-anzoátegui"}, {"valor": 54, "palabra": "defensa-nuestro"}, {"valor": 49, "palabra": "nicolas-maduro"}, {"valor": 47, "palabra": "pueblo-venezolano"}, {"valor": 43, "palabra": "esequibo-venezuela"}, {"valor": 43, "palabra": "referéndum-consultivo"}, {"valor": 41, "palabra": "diplomático-acreditado"}, {"valor": 35, "palabra": "encuentro-cuerpo"}, {"valor": 35, "palabra": "venezuela-presidente"}, {"valor": 34, "palabra": "nuestro-pueblo"}, {"valor": 34, "palabra": "exterior-presidente"}, {"valor": 33, "palabra": "acuerdo-ginebra"}, {"valor": 33, "palabra": "videoconferencia-cuerpo"}, {"valor": 33, "palabra": "territorio-venezolano"}, {"valor": 32, "palabra": "defensa-esequibo"}, {"valor": 32, "palabra": "misión-venezuela"}, {"valor": 32, "palabra": "encuentro-videoconferencia"}]}}