{"2023-11-27-2023-11-27": [{"Influencer": "NicolasMaduro", "Centralidad": 25.18}, {"Influencer": "AntroCanal", "Centralidad": 15.35}, {"Influencer": "DanielgilBello2", "Centralidad": 6.98}, {"Influencer": "Redi_andes", "Centralidad": 5.88}, {"Influencer": "delcyrodriguezv", "Centralidad": 5.28}, {"Influencer": "aecarri", "Centralidad": 5.25}, {"Influencer": "vladimirpadrino", "Centralidad": 5.02}, {"Influencer": "polianalitica", "Centralidad": 4.07}, {"Influencer": "freddyzur", "Centralidad": 3.93}, {"Influencer": "jhonraf44", "Centralidad": 3.71}, {"Influencer": "SurinameCentral", "Centralidad": 3.43}, {"Influencer": "LilianCenteno9", "Centralidad": 3.39}, {"Influencer": "INDIURBANEJA", "Centralidad": 3.16}, {"Influencer": "dcabellor", "Centralidad": 3.05}, {"Influencer": "TarekWiliamSaab", "Centralidad": 2.82}], "2023-11-28-2023-11-28": [{"Influencer": "AntroCanal", "Centralidad": 1.23}, {"Influencer": "TonyRamos_C", "Centralidad": 0.8}, {"Influencer": "Nomasviolenci", "Centralidad": 0.67}, {"Influencer": "NicolasMaduro", "Centralidad": 0.63}, {"Influencer": "jlguerrero64", "Centralidad": 0.61}, {"Influencer": "AlertasMundial", "Centralidad": 0.59}, {"Influencer": "apismeliferaerf", "Centralidad": 0.53}, {"Influencer": "AlbertoRodNews", "Centralidad": 0.46}, {"Influencer": "aecarri", "Centralidad": 0.45}, {"Influencer": "JorgeDa39765010", "Centralidad": 0.39}, {"Influencer": "4F_Mamba", "Centralidad": 0.33}, {"Influencer": "OMontaban55645", "Centralidad": 0.32}, {"Influencer": "MichelCaballero", "Centralidad": 0.27}, {"Influencer": "vladimirpadrino", "Centralidad": 0.26}, {"Influencer": "polianalitica", "Centralidad": 0.25}]}