{"2023-12-09-2023-12-09": {"VEN - Nicolás Maduro - TW": [{"valor": 100, "palabra": "nicolás-maduro"}, {"valor": 21, "palabra": "presidente-venezuela"}, {"valor": 19, "palabra": "presidente-maduro"}, {"valor": 15, "palabra": "pueblo-venezolano"}, {"valor": 14, "palabra": "presidente-guyana"}, {"valor": 12, "palabra": "guayana-esequiba"}, {"valor": 10, "palabra": "nicolas-maduro"}, {"valor": 9, "palabra": "presidente-nicolás"}, {"valor": 9, "palabra": "maduro-presidente"}, {"valor": 8, "palabra": "defensa-esequibo"}, {"valor": 7, "palabra": "bolivariana-venezuela"}, {"valor": 7, "palabra": "nuestro-pueblo"}, {"valor": 7, "palabra": "corina-machado"}, {"valor": 6, "palabra": "venezuela-esequibo"}, {"valor": 6, "palabra": "venezuela-nicolás"}, {"valor": 6, "palabra": "república-bolivariana"}, {"valor": 6, "palabra": "traidores-patria"}, {"valor": 6, "palabra": "venezuela-presidente"}, {"valor": 6, "palabra": "guyana-presidente"}, {"valor": 6, "palabra": "territorio-esequibo"}, {"valor": 6, "palabra": "maduro-esequibo"}, {"valor": 6, "palabra": "maduro-decretos"}, {"valor": 6, "palabra": "esequibo-venezuela"}, {"valor": 6, "palabra": "nuestro-territorio"}, {"valor": 6, "palabra": "esequibo-nuestro"}, {"valor": 6, "palabra": "atleta-venezolana"}, {"valor": 5, "palabra": "comandante-chávez"}, {"valor": 5, "palabra": "presidente-república"}, {"valor": 5, "palabra": "maduro-traidores"}, {"valor": 5, "palabra": "patria-borges"}], "VEN - Referendo Guyana - TW": [{"valor": 96, "palabra": "venezuela-guyana"}, {"valor": 80, "palabra": "esequibo-venezuela"}, {"valor": 56, "palabra": "guyana-venezuela"}, {"valor": 55, "palabra": "venezuela-esequibo"}, {"valor": 52, "palabra": "venezuela-territorio"}, {"valor": 52, "palabra": "nuestro-esequibo"}, {"valor": 49, "palabra": "invasores-guyaneses"}, {"valor": 48, "palabra": "espero-entienda"}, {"valor": 48, "palabra": "entienda-venezuela"}, {"valor": 48, "palabra": "territorio-pelear"}, {"valor": 48, "palabra": "pelear-pelearemos"}, {"valor": 48, "palabra": "pelearemos-nuestra"}, {"valor": 48, "palabra": "nuestra-patria"}, {"valor": 48, "palabra": "patria-moriremos"}, {"valor": 48, "palabra": "moriremos-centímetro"}, {"valor": 48, "palabra": "centímetro-nuestro"}, {"valor": 48, "palabra": "esequibo-invasores"}, {"valor": 26, "palabra": "guayana-esequiba"}, {"valor": 24, "palabra": "territorio-esequibo"}, {"valor": 19, "palabra": "nicolás-maduro"}, {"valor": 19, "palabra": "guyaneses-espero"}, {"valor": 17, "palabra": "disputa-territorial"}, {"valor": 16, "palabra": "guyana-esequibo"}, {"valor": 16, "palabra": "venezuela-venezuela"}, {"valor": 14, "palabra": "disputa-venezuela"}, {"valor": 12, "palabra": "territorial-venezuela"}, {"valor": 12, "palabra": "esequibo-nuestro"}, {"valor": 12, "palabra": "estados-unidos"}, {"valor": 12, "palabra": "acuerdo-ginebra"}, {"valor": 12, "palabra": "esequibo-guyana"}]}}